COPYING
MANIFEST.in
README.rst
buildout.cfg
pyproject.toml
requirements.txt
setup.py
version.txt
bob/__init__.py
bob.ip.binseg.egg-info/PKG-INFO
bob.ip.binseg.egg-info/SOURCES.txt
bob.ip.binseg.egg-info/dependency_links.txt
bob.ip.binseg.egg-info/entry_points.txt
bob.ip.binseg.egg-info/not-zip-safe
bob.ip.binseg.egg-info/requires.txt
bob.ip.binseg.egg-info/top_level.txt
bob/ip/__init__.py
bob/ip/binseg/__init__.py
bob/ip/binseg/configs/__init__.py
bob/ip/binseg/configs/datasets/__init__.py
bob/ip/binseg/configs/datasets/csv.py
bob/ip/binseg/configs/datasets/chasedb1/__init__.py
bob/ip/binseg/configs/datasets/chasedb1/covd.py
bob/ip/binseg/configs/datasets/chasedb1/first_annotator.py
bob/ip/binseg/configs/datasets/chasedb1/mtest.py
bob/ip/binseg/configs/datasets/chasedb1/second_annotator.py
bob/ip/binseg/configs/datasets/chasedb1/ssl.py
bob/ip/binseg/configs/datasets/chasedb1/xtest.py
bob/ip/binseg/configs/datasets/drhagis/__init__.py
bob/ip/binseg/configs/datasets/drhagis/default.py
bob/ip/binseg/configs/datasets/drionsdb/__init__.py
bob/ip/binseg/configs/datasets/drionsdb/expert1.py
bob/ip/binseg/configs/datasets/drionsdb/expert2.py
bob/ip/binseg/configs/datasets/drishtigs1/__init__.py
bob/ip/binseg/configs/datasets/drishtigs1/cup_all.py
bob/ip/binseg/configs/datasets/drishtigs1/cup_any.py
bob/ip/binseg/configs/datasets/drishtigs1/disc_all.py
bob/ip/binseg/configs/datasets/drishtigs1/disc_any.py
bob/ip/binseg/configs/datasets/drive/__init__.py
bob/ip/binseg/configs/datasets/drive/covd.py
bob/ip/binseg/configs/datasets/drive/default.py
bob/ip/binseg/configs/datasets/drive/mtest.py
bob/ip/binseg/configs/datasets/drive/second_annotator.py
bob/ip/binseg/configs/datasets/drive/ssl.py
bob/ip/binseg/configs/datasets/drive/xtest.py
bob/ip/binseg/configs/datasets/hrf/__init__.py
bob/ip/binseg/configs/datasets/hrf/covd.py
bob/ip/binseg/configs/datasets/hrf/default.py
bob/ip/binseg/configs/datasets/hrf/default_fullres.py
bob/ip/binseg/configs/datasets/hrf/mtest.py
bob/ip/binseg/configs/datasets/hrf/ssl.py
bob/ip/binseg/configs/datasets/hrf/xtest.py
bob/ip/binseg/configs/datasets/iostar/__init__.py
bob/ip/binseg/configs/datasets/iostar/covd.py
bob/ip/binseg/configs/datasets/iostar/optic_disc.py
