Metadata-Version: 2.1
Name: bob.ip.binseg
Version: 1.4.0
Summary: Binary Segmentation Benchmark Package for Bob
Home-page: https://gitlab.idiap.ch/bob/bob.ip.binseg
Author: Tim Laibacher
Author-email: tim.laibacher@idiap.ch
Maintainer: Andre Anjos
Maintainer-email: andre.anjos@idiap.ch
License: GPLv3
Keywords: bob
Platform: UNKNOWN
Classifier: Framework :: Bob
Classifier: Development Status :: 5 - Production/Stable
Classifier: Intended Audience :: Science/Research
Classifier: License :: OSI Approved :: GNU General Public License v3 (GPLv3)
Classifier: Natural Language :: English
Classifier: Programming Language :: Python
Classifier: Programming Language :: Python :: 3
Classifier: Topic :: Scientific/Engineering :: Artificial Intelligence
Classifier: Topic :: Software Development :: Libraries :: Python Modules
License-File: COPYING
